UIron/__init__.py
UIron/__main__.py
UIron/config.py
UIron/gui.py
UIron/regex.py
UIron/ui.py
UIron/utils.py
UIron/data/config.json
UIron/data/new.json
UIron-0.0.16.dist-info/LICENSE
UIron-0.0.16.dist-info/METADATA
UIron-0.0.16.dist-info/WHEEL
UIron-0.0.16.dist-info/top_level.txt
UIron-0.0.16.dist-info/RECORD
