Metadata-Version: 2.1
Name: UIron
Version: 0.0.16
Summary: Package for User Interface
Author: Armando Chaparro
Author-email: pylejandria@gmail.com
Keywords: python
Classifier: Development Status :: 1 - Planning
Classifier: Intended Audience :: Developers
Classifier: Programming Language :: Python :: 3
Classifier: Operating System :: Microsoft :: Windows
License-File: LICENSE
Requires-Dist: ttkbootstrap
